afterpaths/__init__.py
afterpaths/analytics.py
afterpaths/cache.py
afterpaths/cli.py
afterpaths/config.py
afterpaths/daily_stats.py
afterpaths/file_tracking.py
afterpaths/git_refs.py
afterpaths/licensing.py
afterpaths/llm.py
afterpaths/local_analytics.py
afterpaths/rules.py
afterpaths/stack.py
afterpaths/storage.py
afterpaths/summarize.py
afterpaths/utils.py
afterpaths/exporters/__init__.py
afterpaths/exporters/base.py
afterpaths/exporters/claude.py
afterpaths/exporters/cursor.py
afterpaths/sources/__init__.py
afterpaths/sources/base.py
afterpaths/sources/claude_code.py
afterpaths/sources/codex.py
afterpaths/sources/cursor.py
afterpaths-0.1.3.dist-info/METADATA
afterpaths-0.1.3.dist-info/WHEEL
afterpaths-0.1.3.dist-info/entry_points.txt
afterpaths-0.1.3.dist-info/RECORD
