Metadata-Version: 2.4
Name: afterpaths
Version: 0.1.3
Summary: Smarter with every session, automatically
License: MIT
Requires-Python: >=3.10
Requires-Dist: click>=8.0.0
Requires-Dist: python-dotenv>=1.0.0
Provides-Extra: all
Requires-Dist: anthropic>=0.39.0; extra == 'all'
Requires-Dist: openai>=1.0.0; extra == 'all'
Provides-Extra: openai
Requires-Dist: openai>=1.0.0; extra == 'openai'
Provides-Extra: summarize
Requires-Dist: anthropic>=0.39.0; extra == 'summarize'
